enocean_webthing/__init__.py
enocean_webthing/app.py
enocean_webthing/enocean_thing.py
enocean_webthing/enocean_webthing.py
enocean_webthing-1.0.1.dist-info/LICENSE
enocean_webthing-1.0.1.dist-info/METADATA
enocean_webthing-1.0.1.dist-info/WHEEL
enocean_webthing-1.0.1.dist-info/entry_points.txt
enocean_webthing-1.0.1.dist-info/top_level.txt
enocean_webthing-1.0.1.dist-info/RECORD
