Metadata-Version: 2.1
Name: enocean-webthing
Version: 1.0.1
Summary: A web connected enocean gateway
Home-page: https://github.com/grro/enocean_webthing
Author: Gregor Roth
Author-email: gregor.roth@web.de
License: UNKNOWN
Keywords: webthings,home automation,enocean,gateway
Platform: UNKNOWN
Classifier: Programming Language :: Python :: 3
Classifier: License :: OSI Approved :: Apache Software License
Classifier: Operating System :: OS Independent
Classifier: Development Status :: 3 - Alpha
Requires-Dist: webthing (==0.15.0)
Requires-Dist: enocean (==0.60.1)
Requires-Dist: redzoo
